MANIFEST.in
README.md
requirements.txt
setup.cfg
setup.py
jaina/__init__.py
jaina/banner.py
jaina/cli.py
jaina/config.py
jaina/exception.py
jaina/history.py
jaina/info.py
jaina/jaina.py
jaina/log.py
jaina/manager.py
jaina/term.py
jaina/util.py
jaina.egg-info/PKG-INFO
jaina.egg-info/SOURCES.txt
jaina.egg-info/dependency_links.txt
jaina.egg-info/entry_points.txt
jaina.egg-info/requires.txt
jaina.egg-info/top_level.txt
jaina/cmd/__init__.py
jaina/cmd/acl_util.py
jaina/cmd/addauth_.py
jaina/cmd/alias_.py
jaina/cmd/cd_.py
jaina/cmd/common.py
jaina/cmd/config_.py
jaina/cmd/create_.py
jaina/cmd/delete_.py
jaina/cmd/delquota_.py
jaina/cmd/exists_.py
jaina/cmd/getAcl_.py
jaina/cmd/get_.py
jaina/cmd/help_.py
jaina/cmd/history_.py
jaina/cmd/kaixin_.py
jaina/cmd/listquota_.py
jaina/cmd/ls_.py
jaina/cmd/os_.py
jaina/cmd/printwatches_.py
jaina/cmd/quit_.py
jaina/cmd/reconfig_.py
jaina/cmd/redo_.py
jaina/cmd/removewatches_.py
jaina/cmd/setAcl_.py
jaina/cmd/set_.py
jaina/cmd/setquota_.py
jaina/cmd/stat_.py
jaina/cmd/sync_.py
jaina/view/__init__.py
jaina/view/common.py
jaina/view/plain_.py
jaina/view/tree_.py