Metadata-Version: 2.1
Name: jaina
Version: 1.0.1
Summary: A Powerful Zookeeper Client Tool
Home-page: https://github.com/kaixinbaba/jaina
Author: Jeff Xun
Author-email: 452914639@qq.com
License: BSD
Download-URL: https://github.com/kaixinbaba/jaina/tarball/1.0.1
Platform: UNKNOWN
Classifier: Development Status :: 3 - Alpha
Classifier: Intended Audience :: Developers
Classifier: Programming Language :: Python :: 3
Classifier: Programming Language :: Python :: 3.6
Classifier: Programming Language :: Python :: 3.7
Classifier: Programming Language :: Python :: 3.8
